bharat/__init__.py
bharat/bharat.py
bharat/states/__init__.py
bharat/states/objects.py
bharat/states/states.json
bharat/states/states.py
bharat-0.1.dist-info/LICENSE
bharat-0.1.dist-info/METADATA
bharat-0.1.dist-info/WHEEL
bharat-0.1.dist-info/top_level.txt
bharat-0.1.dist-info/RECORD
