Metadata-Version: 2.1
Name: bharat
Version: 0.1
Summary: India states metadata
Home-page: https://github.com/bytebaker/bharat
Author: Shraddha Kishan
Author-email: shraddha.kishan@gmail.com
License: BSD
Platform: any
Classifier: Programming Language :: Python :: 3
